openid/association.py
openid/dh.py
openid/kvform.py
openid/urinorm.py
openid/fetchers.py
openid/__init__.py
openid/sreg.py
openid/oidutil.py
openid/message.py
openid/extension.py
openid/cryptutil.py
openid/consumer/html_parse.py
openid/consumer/__init__.py
openid/consumer/discover.py
openid/consumer/consumer.py
openid/store/filestore.py
openid/store/interface.py
openid/store/nonce.py
openid/store/__init__.py
openid/store/memstore.py
openid/store/sqlstore.py
openid/yadis/etxrd.py
openid/yadis/manager.py
openid/yadis/filters.py
openid/yadis/accept.py
openid/yadis/__init__.py
openid/yadis/xri.py
openid/yadis/services.py
openid/yadis/xrires.py
openid/yadis/discover.py
openid/yadis/parsehtml.py
openid/yadis/constants.py
openid/server/__init__.py
openid/server/trustroot.py
openid/server/server.py
openid/extensions/__init__.py
openid/extensions/sreg.py
openid/extensions/ax.py
openid/extensions/draft/__init__.py
openid/extensions/draft/pape2.py
openid/extensions/draft/pape5.py
scratch_openid-2.3.1.dist-info/DESCRIPTION.rst
scratch_openid-2.3.1.dist-info/METADATA
scratch_openid-2.3.1.dist-info/WHEEL
scratch_openid-2.3.1.dist-info/metadata.json
scratch_openid-2.3.1.dist-info/RECORD
scratch_openid-2.3.1.dist-info/top_level.txt
